setup.py
Demographics_box/Age.py
Demographics_box/First_name.py
Demographics_box/Group.py
Demographics_box/Job.py
Demographics_box/Last_name.py
Demographics_box/People.py
Demographics_box/US_State.py
Demographics_box/__init__.py
Demographics_box/__main__.py
Demographics_box.egg-info/PKG-INFO
Demographics_box.egg-info/SOURCES.txt
Demographics_box.egg-info/dependency_links.txt
Demographics_box.egg-info/top_level.txt