Metadata-Version: 1.1
Name: Demographics-box
Version: 1.24
Summary: A package to generate list of people
Home-page: UNKNOWN
Author: Emmanuel Sevrin
Author-email: UNKNOWN
License: UNKNOWN
Platform: UNKNOWN
Classifier: Programming Language :: Python :: 3
Classifier: License :: OSI Approved :: MIT License
Classifier: Operating System :: OS Independent
